MANIFEST.in
README.rst
setup.py
RobotS2LScreenshot/__init__.py
RobotS2LScreenshot.egg-info/PKG-INFO
RobotS2LScreenshot.egg-info/SOURCES.txt
RobotS2LScreenshot.egg-info/dependency_links.txt
RobotS2LScreenshot.egg-info/requires.txt
RobotS2LScreenshot.egg-info/top_level.txt
RobotS2LScreenshot.egg-info/zip-safe
test/baseline-Screenshot cropped to myform locator.png
test/baseline-Screenshot cropped with invalid locator.png
test/baseline-Screenshot masked with invalid locator.png
test/baseline-Screenshot masked with invalid rectangle.png
test/baseline-Screenshot with 1st and 4th quadrant masked using rectangle.png
test/baseline-Screenshot with header and footer masked using locator.png
test/test.html
test/test_robots2lscreenshot.py
test/test_robots2lscreenshot.txt