Metadata-Version: 1.1
Name: RobotS2LScreenshot
Version: 0.1.1
Summary: Provides additional keywords to augment screenshots capabilities of RobotFramework's Selenium2Library, namely cropping and masking to help with perceptual diff testing.
Home-page: https://github.com/canaryhealth/RobotS2LScreenshot
Author: UNKNOWN
Author-email: UNKNOWN
License: MIT
Platform: any
Classifier: Development Status :: 4 - Beta
Classifier: Environment :: Web Environment
Classifier: Intended Audience :: Developers
Classifier: License :: OSI Approved :: MIT License
Classifier: Natural Language :: English
Classifier: Operating System :: OS Independent
Classifier: Programming Language :: Python
Classifier: Topic :: Software Development :: Quality Assurance
Classifier: Topic :: Software Development :: Testing
